{
  "project_info": {
    "project_number": "475075913010",
    "firebase_url": "https://mydynamicadapter.firebaseio.com",
    "project_id": "mydynamicadapter",
    "storage_bucket": "mydynamicadapter.appspot.com"
  },
  "client": [
    {
      "client_info": {
        "mobilesdk_app_id": "1:475075913010:android:67c0b220c18a299a",
        "android_client_info": {
          "package_name": "com.converter.indra.mydynamicadapter"
        }
      },
      "oauth_client": [
        {
          "client_id": "475075913010-uu5cado6iq4p74e7vhjpdtk4ddk4htrj.apps.googleusercontent.com",
          "client_type": 3
        }
      ],
      "api_key": [
        {
          "current_key": "AIzaSyDWcenYg-28AFqnkFRWAEvnCF_VV11N-1I"
        }
      ],
      "services": {
        "analytics_service": {
          "status": 1
        },
        "appinvite_service": {
          "status": 1,
          "other_platform_oauth_client": []
        },
        "ads_service": {
          "status": 2
        }
      }
    }
  ],
  "configuration_version": "1"
}